dialog.py
python2_pythondialog-3.5.1.dist-info/AUTHORS
python2_pythondialog-3.5.1.dist-info/COPYING
python2_pythondialog-3.5.1.dist-info/COPYING.Sphinx
python2_pythondialog-3.5.1.dist-info/METADATA
python2_pythondialog-3.5.1.dist-info/WHEEL
python2_pythondialog-3.5.1.dist-info/top_level.txt
python2_pythondialog-3.5.1.dist-info/RECORD
