Metadata-Version: 2.1
Name: python2-pythondialog
Version: 3.5.1
Summary: A Python interface to the UNIX dialog utility and mostly-compatible programs (Python 2 backport)
Home-page: http://pythondialog.sourceforge.net/
Author: Robb Shecter
Author-email: robb@acm.org
Maintainer: Florent Rougon
Maintainer-email: f.rougon@free.fr
License: UNKNOWN
Project-URL: Issue tracker, https://sourceforge.net/p/pythondialog/_list/tickets
Project-URL: Git repository, https://sourceforge.net/p/pythondialog/code/
Project-URL: Documentation, http://pythondialog.sourceforge.net/doc/
Project-URL: SourceForge project page, https://sourceforge.net/projects/pythondialog
Project-URL: Mailing list, https://sourceforge.net/p/pythondialog/mailman/
Keywords: dialog,ncurses,Xdialog,text-mode interface,terminal
Platform: Unix
Classifier: Programming Language :: Python :: 2
Classifier: Programming Language :: Python :: 2.6
Classifier: Programming Language :: Python :: 2.7
Classifier: Development Status :: 7 - Inactive
Classifier: Environment :: Console :: Curses
Classifier: Intended Audience :: Developers
Classifier: License :: OSI Approved :: GNU Library or Lesser General Public License (LGPL)
Classifier: Operating System :: Unix
Classifier: Topic :: Software Development :: Libraries :: Python Modules
Classifier: Topic :: Software Development :: User Interfaces
Classifier: Topic :: Software Development :: Widget Sets
Requires-Python: >=2.6, <3
